nightingale/__init__.py
nightingale/distribution/Distribution.py
nightingale/distribution/__init__.py
nightingale/distribution/probability_density_curve.py
nightingale/distribution/functions/__init__.py
nightingale/distribution/functions/categorical_distribution.py
nightingale/distribution/functions/multiselect_distribution.py
nightingale/distribution/functions/normal_distribution.py
nightingale/distribution/functions/uniform_distribution.py
nightingale/helpers/SortedDict.py
nightingale/helpers/__init__.py
nightingale/plots/__init__.py
nightingale/plots/density_plot.py
nightingale/plots/line_plot.py
nightingale/plots/scatter_plot.py
nightingale/plots/plot_helpers/__init__.py
nightingale/plots/plot_helpers/convert_collections_to_df.py
nightingale/plots/plot_helpers/get_plot_kwargs.py
nightingale/plots/plot_helpers/infer_plot_arguments.py
nightingale/plots/plot_helpers/melt.py
nightingale-2025.2.6.2.dist-info/LICENSE
nightingale-2025.2.6.2.dist-info/METADATA
nightingale-2025.2.6.2.dist-info/WHEEL
nightingale-2025.2.6.2.dist-info/top_level.txt
nightingale-2025.2.6.2.dist-info/RECORD
